hym/__init__.py
opcal-0.0.0.dist-info/LICENSE
opcal-0.0.0.dist-info/METADATA
opcal-0.0.0.dist-info/WHEEL
opcal-0.0.0.dist-info/top_level.txt
opcal-0.0.0.dist-info/RECORD
