Metadata-Version: 2.1
Name: opcal
Version: 0.0.0
License-File: LICENSE
Requires-Dist: openpyxl
Requires-Dist: numpy
Requires-Dist: matplotlib
Requires-Dist: pandas
